rensa-0.2.9.dist-info/METADATA
rensa-0.2.9.dist-info/WHEEL
rensa-0.2.9.dist-info/licenses/LICENSE
rensa/__init__.py
rensa/rensa.cpython-39-s390x-linux-gnu.so
rensa-0.2.9.dist-info/RECORD
