Metadata-Version: 2.4
Name: rensa
Version: 0.2.9
Classifier: Programming Language :: Rust
Classifier: Programming Language :: Python :: Implementation :: CPython
Classifier: Programming Language :: Python :: Implementation :: PyPy
License-File: LICENSE
Summary: High-performance MinHash implementation in Rust with Python bindings - 40x faster than datasketch
Author-email: Luis Cardoso <luis@luiscardoso.dev>
License: MIT
Requires-Python: >=3.8
Project-URL: Homepage, https://github.com/beowolx/rensa
Project-URL: Repository, https://github.com/beowolx/rensa
Project-URL: Issues, https://github.com/beowolx/rensa/issues
